socian_auth/__init__.py
socian_auth/api_client.py
socian_auth/models.py
socian_auth-0.0.8.dist-info/LICENSE
socian_auth-0.0.8.dist-info/METADATA
socian_auth-0.0.8.dist-info/WHEEL
socian_auth-0.0.8.dist-info/top_level.txt
socian_auth-0.0.8.dist-info/RECORD
