Metadata-Version: 2.1
Name: socian-auth
Version: 0.0.8
Summary: Socian Auth Python SDK for authentication and user management
Home-page: https://github.com/Socian-Ltd//socian_auth_sdk_python
Author: Socian Ltd.
Author-email: admin@socian.ai
License: MIT
Project-URL: Documentation, https://github.com/Socian-Ltd/socian_auth_sdk_python.git
Project-URL: Source, https://github.com/Socian-Ltd/socian_auth_sdk_python.git
Project-URL: Bug Reports, https://github.com/Socian-Ltd/socian_auth_sdk_python/issues
Keywords: socian auth authentication user-management sdk
Classifier: Development Status :: 5 - Production/Stable
Classifier: Intended Audience :: Developers
Classifier: Topic :: Software Development :: Build Tools
Classifier: Programming Language :: Python :: 3
Classifier: Programming Language :: Python :: 3.6
Classifier: Programming Language :: Python :: 3.7
Classifier: Programming Language :: Python :: 3.8
Classifier: Programming Language :: Python :: 3.9
Classifier: Programming Language :: Python :: 3 :: Only
Classifier: License :: OSI Approved :: MIT License
Classifier: Operating System :: OS Independent
Requires-Python: >=3.6
License-File: LICENSE
Requires-Dist: requests
